{"gen-examples": "false", "pub_url": "ehaas@healthedatainc.com", "spreadsheets": ["identifier-free-reference-profile-spreadsheet.xml", "patient-on-usprofile-spreadsheet.xml", "template-profile-spreadsheet.xml"], "valuesets": [], "title": "IG-Test", "dependencyList": [{"location": "http://hl7.org/fhir/us/core/stu1/", "source": "uscore", "name": "uscore"}], "extensions": ["template-blah", "template-complex"], "resources": {"StructureDefinition/template-profile-on-profile": {"defns": "StructureDefinition-template-profile-on-profile-definitions.html", "base": "StructureDefinition-template-profile-on-profile.html"}, "AllergyIntolerance/example": {"source": "allergyintolerance-example.xml", "base": "AllergyIntolerance-example.html"}, "Basic/diet": {"source": "diet.xml", "base": "Basic-diet.html"}, "StructureDefinition/ifr": {"defns": "StructureDefinition-ifr-definitions.html", "base": "StructureDefinition-ifr.html"}, "ValueSet/blah-codes": {"base": "ValueSet-blah-codes.html"}, "CodeSystem/blah-codes": {"base": "CodeSystem-blah-codes.html"}, "MedicationRequest/uscore-mo1": {"source": "uscore-mo1.xml", "base": "MedicationRequest-uscore-mo1.html"}, "StructureMap/Foo": {"base": "StructureMap-Foo.html"}, "StructureDefinition/template-basic2": {"defns": "StructureDefinition-template-basic2-definitions.html", "source": "structuredefinition-template-basic2.xml", "base": "StructureDefinition-template-basic2.html"}, "StructureDefinition/template-profile-on-profile2": {"defns": "StructureDefinition-template-profile-on-profile2-definitions.html", "source": "structuredefinition-template-profile-on-profile2.xml", "base": "StructureDefinition-template-profile-on-profile2.html"}, "StructureDefinition/template-complex": {"defns": "StructureDefinition-template-complex-definitions.html", "base": "StructureDefinition-template-complex.html"}, "Observation/example": {"source": "obs.xml", "base": "Observation-example.html"}, "StructureDefinition/template-basic": {"defns": "StructureDefinition-template-basic-definitions.html", "base": "StructureDefinition-template-basic.html"}, "CapabilityStatement/client": {"source": "capabilitystatement-client.xml", "base": "CapabilityStatement-client.html"}, "CapabilityStatement/server": {"source": "capabilitystatement-server.xml", "base": "CapabilityStatement-server.html"}, "StructureDefinition/template-blah": {"defns": "StructureDefinition-template-blah-definitions.html", "base": "StructureDefinition-template-blah.html"}, "SearchParameter/blah": {"source": "searchparameter-blah.xml", "base": "SearchParameter-blah.html"}}, "extraTemplates": ["mappings"], "igtemplate-dir": "/Users/ehaas/Documents/FHIR/IG-Template2/", "structuremaps": ["Foo"], "fixed-business-version": "0.0.0", "searches": [], "special-urls": [], "jurisdiction": "US", "paths": {"temp": "temp", "txCache": "txCache", "qa": "qa", "specification": "http://build.fhir.org", "pages": ["pages", "../IG-Test2/pages"], "output": "../IG-Test2/output", "resources": ["../IG-Test2/resources", "../IG-Test2/examples"]}, "defaults": {"CodeSystem": {"template-base": "codesys.html"}, "Any": {"template-format": "format.html", "template-base": "base.html"}, "MedicationRequest": {"template-base": "ex.html"}, "OperationDefinition": {"template-base": "op.html"}, "AllergyIntolerance": {"template-base": "ex.html"}, "ValueSet": {"template-base": "vs.html"}, "Observation": {"template-base": "ex.html"}, "ConceptMap": {"template-base": "cm.html"}, "CapabilityStatement": {"template-base": "capst.html"}, "StructureMap": {"profiles": false, "script": false, "content": false, "template-base": "base.html"}, "Basic": {"template-base": "ex.html"}, "StructureDefinition": {"template-defns": "sd-definitions.html", "template-mappings": "sd-mappings.html", "template-base": "sd.html"}}, "codesystems": ["blah-codes"], "version": "3.0.1", "broken-links": "warning", "publisher": "Health eData Inc", "working-dir": "/Users/ehaas/Documents/FHIR/Test2/", "source": "ig.xml", "canonicalBase": "http://www.fhir.org/guides/ig-template", "no-inactive-codes": "false", "status": "draft", "do-transforms": "false", "sct-edition": "http://snomed.info/sct/731000124108", "tool": "jekyll"}